TrabajoPracticoFinal_Estacionamiento/Con Antibounce/fsm_estacionamiento.v
module fsm_estacionamiento(
    input wire clk,
    input wire reset,
    input wire a,
    input wire b,
    output reg [2:0] cantidad // Conteo de autos en el estacionamiento

);
    wire ai, bi, clki, rsti;
    assign ai = ~a;
    assign bi = ~b;
    assign clki = ~clk;
    assign rsti = ~reset;
    reg [2:0] count = 3'd0; // Contador interno de autos
    localparam [2:0]
        reposo = 3'b000,      // Estado inicial - esperando acción
        entrada1 = 3'b001,    // Primera fase de entrada
        entrada2 = 3'b010,    // Segunda fase de entrada  
        entrada3 = 3'b011,    // Tercera fase - confirmando entrada
        salida1 = 3'b100,     // Primera fase de salida
        salida2 = 3'b101,     // Segunda fase de salida
        salida3 = 3'b110,     // Tercera fase - confirmando salida
        estado_invalido = 3'b111; 
    
    reg [2:0] estado_actual, estado_siguiente;
    reg sum, res; // Señales de suma y resta para el contador
    //reg entrada_reg, salida_reg;
    always @(posedge clki or posedge rsti) begin
        if (rsti) begin
            estado_actual <= reposo;
            count <= 3'd0; // Conteo inicia en 0 al resetear
        end else if (sum && count < 3'b111) begin
            count <= count + 1'b1; // Suma si solo entra auto
            estado_actual = estado_siguiente;
        end else if (res && count > 3'b000) begin
            count <= count - 1'b1; // Resta si solo sale auto y no está vacío
            estado_actual = estado_siguiente;
        end else
            estado_actual = estado_siguiente;
    end

always @(*) begin
    estado_siguiente = estado_actual; // Por defecto, mantener el estado actual
    cantidad = count; // Actualiza la salida con el conteo actual
    sum = 0;
    res = 0;
    case (estado_actual)
        reposo: begin
            if (ai && !bi)
                estado_siguiente = entrada1;
            else if (!ai && bi)
                estado_siguiente = salida1;
            else if (ai && bi)
                estado_siguiente = estado_invalido; // Estado reposo
        end
        entrada1: begin
            if (ai && bi)
                estado_siguiente = entrada2;
            else if (!ai && !bi) begin
                estado_siguiente = reposo;
            end else if (ai && !bi)
                estado_siguiente = entrada1;
        end
        entrada2: begin
            if (!ai && bi)
                estado_siguiente = entrada3;
            else if (ai && !bi) begin
                estado_siguiente = entrada1;
            end else if (ai && bi)
                estado_siguiente = entrada2; //Secuencia incompleta
        end
        entrada3: begin
            if (!ai && !bi) begin
                sum = 1; // Pulsar entrada
                estado_siguiente = reposo;
            end else if (ai && bi) begin
                estado_siguiente = entrada2; // Secuencia de salida completa
            end else if (!ai && bi) begin
                estado_siguiente = entrada3; // Secuencia incompleta
        end
        end
        salida1: begin
            if (ai && bi)
                estado_siguiente = salida2;
            else if (!ai && !bi) begin
                estado_siguiente = reposo;
            end else if (!ai && bi)
                estado_siguiente = salida1; // Estado invalido
        end
        salida2: begin
            if (ai && !bi)
                estado_siguiente = salida3;
            else if (!ai && bi) begin
                estado_siguiente = salida1;
            end else if (ai && bi)
                estado_siguiente = salida2; // Secuencia incompleta
        end
        salida3: begin
            if (!ai && !bi) begin
                res = 1; // Pulsar salida
                estado_siguiente = reposo;
            end else if (ai && bi) begin
                estado_siguiente = salida2; // Secuencia de entrada completa
            end else if (ai && !bi) begin
                estado_siguiente = salida3; // Secuencia incompleta
            end
        end
        estado_invalido: begin
            // Si se llega a un estado invalido, se resetea al estado inicial
            estado_siguiente = reposo;
        end
        default: begin
            estado_siguiente = reposo; // Reseteo a estado inicial por defecto
        end
    endcase
end

//assign entrada = entrada_reg;
//assign salida = salida_reg;
endmodule

TrabajoPracticoFinal_Estacionamiento/Con Antibounce/estacionamiento_tb.v
`timescale 1ns / 1ps

module tb_fsm_estacionamiento();

    reg clk;
    reg reset;
    reg a;
    reg b;
    wire [2:0] ocupacion;

    fsm_estacionamiento dut (
        .clk(clk),
        .reset(reset),
        .a(a),
        .b(b),
        .cantidad(ocupacion)
    );

    always begin
        clk = 0; #10;
        clk = 1; #10;
    end

    task apply_reset();
        begin
            reset = 0; a = 0; b = 0; #40;
            reset = 1; #20;
        end
    endtask

    task entrada_completa();
        begin
            a = 1; b = 0; #40;
            a = 1; b = 1; #40;
            a = 0; b = 1; #40;
            a = 0; b = 0; #40;
        end
    endtask

    task salida_completa();
        begin
            a = 0; b = 1; #40;
            a = 1; b = 1; #40;
            a = 1; b = 0; #40;
            a = 0; b = 0; #40;
        end
    endtask

    initial begin
        $dumpfile("estacionamiento_tb.vcd");
        $dumpvars(0, tb_fsm_estacionamiento);

        clk = 0; reset = 0; a = 0; b = 0;

        apply_reset();

        entrada_completa();

        entrada_completa();

        entrada_completa();

        salida_completa();

        salida_completa();
        
        salida_completa();

        #100;
        $finish;
    end

endmodule

TrabajoPracticoFinal_Estacionamiento/Con Antibounce/estacionamiento_tb.vcd
$date
	Fri Jun 20 21:41:08 2025
$end
$version
	Icarus Verilog
$end
$timescale
	1ps
$end
$scope module tb_fsm_estacionamiento $end
$var wire 3 ! ocupacion [2:0] $end
$var reg 1 " a $end
$var reg 1 # b $end
$var reg 1 $ clk $end
$var reg 1 % reset $end
$scope module dut $end
$var wire 1 " a $end
$var wire 1 & ai $end
$var wire 1 # b $end
$var wire 1 ' bi $end
$var wire 1 $ clk $end
$var wire 1 ( clki $end
$var wire 1 % reset $end
$var wire 1 ) rsti $end
$var parameter 3 * entrada1 $end
$var parameter 3 + entrada2 $end
$var parameter 3 , entrada3 $end
$var parameter 3 - estado_invalido $end
$var parameter 3 . reposo $end
$var parameter 3 / salida1 $end
$var parameter 3 0 salida2 $end
$var parameter 3 1 salida3 $end
$var reg 3 2 cantidad [2:0] $end
$var reg 3 3 count [2:0] $end
$var reg 3 4 estado_actual [2:0] $end
$var reg 3 5 estado_siguiente [2:0] $end
$var reg 1 6 res $end
$var reg 1 7 sum $end
$upscope $end
$scope task apply_reset $end
$upscope $end
$scope task entrada_completa $end
$upscope $end
$scope task salida_completa $end
$upscope $end
$upscope $end
$enddefinitions $end
$comment Show the parameter values. $end
$dumpall
b110 1
b101 0
b100 /
b0 .
b111 -
b11 ,
b10 +
b1 *
$end
#0
$dumpvars
07
06
b111 5
b0 4
b0 3
b0 2
1)
1(
1'
1&
0%
0$
0#
0"
b0 !
$end
#10000
0(
1$
#20000
1(
0$
#30000
0(
1$
#40000
b0 5
b111 4
1(
0)
0$
1%
#50000
0(
1$
#60000
b0 4
b100 5
1(
0&
0$
1"
#70000
0(
1$
#80000
b100 4
1(
0$
#90000
0(
1$
#100000
b0 4
b0 5
1(
0'
0$
1#
#110000
0(
1$
#120000
1(
0$
#130000
0(
1$
#140000
b1 4
b1 5
1(
1&
0$
0"
#150000
0(
1$
#160000
1(
0$
#170000
0(
1$
#180000
b10 4
b10 5
1(
1'
0$
0#
#190000
0(
1$
#200000
1(
0$
#210000
0(
1$
#220000
b11 4
b11 5
1(
0&
0$
1"
#230000
0(
1$
#240000
1(
0$
#250000
0(
1$
#260000
b1 !
b1 2
b1 3
b0 4
b0 5
07
1(
0'
0$
1#
#270000
0(
1$
#280000
1(
0$
#290000
0(
1$
#300000
b1 4
b1 5
1(
1&
0$
0"
#310000
0(
1$
#320000
1(
0$
#330000
0(
1$
#340000
b10 4
b10 5
1(
1'
0$
0#
#350000
0(
1$
#360000
1(
0$
#370000
0(
1$
#380000
b11 4
b11 5
1(
0&
0$
1"
#390000
0(
1$
#400000
1(
0$
#410000
0(
1$
#420000
b10 !
b10 2
b10 3
b0 4
b0 5
07
1(
0'
0$
1#
#430000
0(
1$
#440000
1(
0$
#450000
0(
1$
#460000
b1 4
b1 5
1(
1&
0$
0"
#470000
0(
1$
#480000
1(
0$
#490000
0(
1$
#500000
b10 4
b10 5
1(
1'
0$
0#
#510000
0(
1$
#520000
1(
0$
#530000
0(
1$
#540000
b1 4
b1 5
1(
0'
0$
1#
#550000
0(
1$
#560000
1(
0$
#570000
0(
1$
#580000
b0 4
b0 5
1(
0&
0$
1"
#590000
0(
1$
#600000
1(
0$
#610000
0(
1$
#620000
b100 4
b100 5
1(
1'
0$
0#
#630000
0(
1$
#640000
1(
0$
#650000
0(
1$
#660000
b101 4
b101 5
1(
1&
0$
0"
#670000
0(
1$
#680000
1(
0$
#690000
0(
1$
#700000
b110 4
b110 5
1(
0'
0$
1#
#710000
0(
1$
#720000
1(
0$
#730000
0(
1$
#740000
b1 !
b1 2
b1 3
b0 4
b0 5
06
1(
0&
0$
1"
#750000
0(
1$
#760000
1(
0$
#770000
0(
1$
#780000
b100 4
b100 5
1(
1'
0$
0#
#790000
0(
1$
#800000
1(
0$
#810000
0(
1$
#820000
b101 4
b101 5
1(
1&
0$
0"
#830000
0(
1$
#840000
1(
0$
#850000
0(
1$
#860000
b110 4
b110 5
1(
0'
0$
1#
#870000
0(
1$
#880000
1(
0$
#890000
0(
1$
#900000
b0 !
b0 2
b0 3
b0 4
b0 5
06
1(
0&
0$
1"
#910000
0(
1$
#920000
1(
0$
#930000
0(
1$
#940000
b100 4
b100 5
1(
1'
0$
0#
#950000
0(
1$
#960000
1(
0$
#970000
0(
1$
#980000
b101 4
b101 5
1(
1&
0$
0"
